<nml_record name="horizontal_advection" mode="init" configuration="horizontal_advection">
        <nml_option name="config_horizontal_advection_temperature" type="real" default_value="15.0" units="deg C"
            description="Temperature of the ocean."
            possible_values="Any real number"
        />
        <nml_option name="config_horizontal_advection_salinity" type="real" default_value="35.0" units="PSU"
            description="Salinity of the surface of the ocean."
            possible_values="Any real number"
        />
        <nml_option name="config_horizontal_advection_x_cent" type="real" default_value="400" units="m"
            description="X value for center of tracer circule"
            possible_values="Any real number greater than zero."
        />
        <nml_option name="config_horizontal_advection_y_cent" type="real" default_value="400" units="m"
            description="y value for center of tracer circule"
            possible_values="Any real number greater than zero."
        />
        <nml_option name="config_horizontal_advection_tracer_radius" type="real" default_value="100" units="m"
            description="Radus of tracer circule"
            possible_values="Any real number greater than zero."
        />
        <nml_option name="config_horizontal_advection_meridionalC" type="real" default_value=".5" units="m*s^{-1}"
            description="Constant Meridional Velocity"
            possible_values="Any real number greater than zero."                                           
        />
        <nml_option name="config_horizontal_advection_zonalC" type="real" default_value=".5" units="m*s^{-1}"
            description="Constant zonal Velocity"
            possible_values="Any real number greater than zero."                                           
        />
        <nml_option name="config_horizontal_advection_gaussian_width" type="real" default_value="10" units="m^{2}"
            description="width of gaussian hill"
            possible_values="Any real number greater than zero"
        />
</nml_record>
